tinyloader/__init__.py
tinyloader/loader.py
tinyloader-0.1.5.dist-info/licenses/LICENSE
tinyloader-0.1.5.dist-info/METADATA
tinyloader-0.1.5.dist-info/WHEEL
tinyloader-0.1.5.dist-info/top_level.txt
tinyloader-0.1.5.dist-info/RECORD
