Metadata-Version: 2.4
Name: tinyloader
Version: 0.1.5
Summary: A minimalist multiprocessing data loader for tinygrad
Project-URL: Homepage, https://github.com/LaunchPlatform/tinyloader
Project-URL: Repository, https://github.com/LaunchPlatform/tinyloader.git
Requires-Python: >=3.11
License-File: LICENSE
Requires-Dist: numpy>=2.3.0
Requires-Dist: tinygrad>=0.10.3
Dynamic: license-file
